stream_write_ods.py
stream_write_ods-0.0.25.dist-info/METADATA
stream_write_ods-0.0.25.dist-info/WHEEL
stream_write_ods-0.0.25.dist-info/licenses/LICENSE
stream_write_ods-0.0.25.dist-info/RECORD
