Metadata-Version: 2.3
Name: stream-write-ods
Version: 0.0.25
Summary: Python function to construct an ODS spreadsheet on the fly - without having to store the entire file in memory or disk
Project-URL: Source, https://github.com/uktrade/stream-write-ods
Author-email: Department for International Trade <sre@digital.trade.gov.uk>
License-File: LICENSE
Classifier: License :: OSI Approved :: MIT License
Classifier: Programming Language :: Python :: 3
Classifier: Topic :: System :: Archiving :: Compression
Requires-Python: >=3.7.1
Requires-Dist: stream-zip>=0.0.64
Provides-Extra: dev
Requires-Dist: coverage; extra == 'dev'
Requires-Dist: pandas-ods-reader; extra == 'dev'
Requires-Dist: pytest; extra == 'dev'
Requires-Dist: pytest-cov; extra == 'dev'
